skit_calls/__init__.py
skit_calls/calls.py
skit_calls/cli.py
skit_calls/constants.py
skit_calls/data/__init__.py
skit_calls/data/db.py
skit_calls/data/model.py
skit_calls/data/mutators.py
skit_calls/data/query.py
skit_calls/utils.py
skit_calls-0.2.56.dist-info/LICENSE
skit_calls-0.2.56.dist-info/METADATA
skit_calls-0.2.56.dist-info/WHEEL
skit_calls-0.2.56.dist-info/entry_points.txt
skit_calls-0.2.56.dist-info/RECORD
